xatelite/__init__.py
xatelite/xatelite.py
xatelite-0.1.2.dist-info/DESCRIPTION.rst
xatelite-0.1.2.dist-info/METADATA
xatelite-0.1.2.dist-info/RECORD
xatelite-0.1.2.dist-info/WHEEL
xatelite-0.1.2.dist-info/entry_points.txt
xatelite-0.1.2.dist-info/metadata.json
xatelite-0.1.2.dist-info/top_level.txt
