Metadata-Version: 2.0
Name: xatelite
Version: 0.1.2
Summary: A Python3 LaTeX over SSH/HTTP service
Home-page: https://github.com/enricozb/XaTeLite
Author: Enrico Borba
Author-email: enricozb@gmail.com
License: MIT
Keywords: latex,ssh
Platform: UNKNOWN
Requires-Python: >=3
Requires-Dist: flask
